intersection/__init__.py
intersection/cli.py
intersection/data.py
intersection/game.py
intersection/telegram_bot.py
intersection-0.0.2.dist-info/entry_points.txt
intersection-0.0.2.dist-info/WHEEL
intersection-0.0.2.dist-info/METADATA
intersection-0.0.2.dist-info/RECORD
