Metadata-Version: 2.1
Name: intersection
Version: 0.0.2
Summary: Telegram based version of a text based game where two players try to find the same word.
Home-page: https://github.com/gruvw/intersection
Author: gruvw
Author-email: gruvw.dev@gmail.com
Requires-Python: >=3.10,<4.0
Classifier: Programming Language :: Python :: 3
Classifier: Programming Language :: Python :: 3.10
Requires-Dist: Unidecode (>=1.3.4,<2.0.0)
Requires-Dist: click (>=8.1.3,<9.0.0)
Requires-Dist: nanoid (>=2.0.0,<3.0.0)
Requires-Dist: python-dotenv (>=0.20.0,<0.21.0)
Requires-Dist: python-telegram-bot (>=13.13,<14.0)
